<?xml version="1.0" encoding="utf-8" ?><dwsync><file name="jqueryFileTree.asp" server="192.168.34.5" local="3294807126" remote="318763443872896692" Dst="-1" /><file name="jqueryFileTree.aspx" server="192.168.34.5" local="3329712118" remote="318763443872896692" Dst="-1" /><file name="jqueryFileTree.cf" server="192.168.34.5" local="3297590156" remote="318763443872896692" Dst="-1" /><file name="jqueryFileTree.php" server="192.168.34.5" local="3480039766" remote="318763443872900232" Dst="-1" /><file name="jqueryFileTree.jsp" server="192.168.34.5" local="3353189982" remote="318763443872896692" Dst="-1" /><file name="jqueryFileTree.pl" server="192.168.34.5" local="3317431936" remote="318763443872896692" Dst="-1" /><file name="jqueryFileTree.py" server="192.168.34.5" local="3297590354" remote="318763443872896692" Dst="-1" /><file name="jqueryFileTree.rb" server="192.168.34.5" local="3298766486" remote="318763443872896692" Dst="-1" /><file name="jqueryFileTree_huck.lasso" server="192.168.34.5" local="3297590372" remote="318763443872896692" Dst="-1" /><file name="jqueryFileTree_sabourdin.lasso" server="192.168.34.5" local="3294739072" remote="318763443872896692" Dst="-1" /><file name="jqueryFileTree.jsp" server="Macintosh HD/Applications/MAMP/htdocs/Final/" local="3353189982" remote="318763443746086494" Dst="-1" /><file name=".DS_Store" server="Macintosh HD/Applications/MAMP/htdocs/Final/" local="3480036446" remote="318763443872932958" Dst="-1" /><file name="jqueryFileTree.asp" server="Macintosh HD/Applications/MAMP/htdocs/Final/" local="3294807126" remote="318763443687703638" Dst="-1" /><file name="jqueryFileTree.aspx" server="Macintosh HD/Applications/MAMP/htdocs/Final/" local="3329712118" remote="318763443722608630" Dst="-1" /><file name="jqueryFileTree.cf" server="Macintosh HD/Applications/MAMP/htdocs/Final/" local="3297590156" remote="318763443690486668" Dst="-1" /><file name="jqueryFileTree.php" server="Macintosh HD/Applications/MAMP/htdocs/Final/" local="3480039766" remote="318763443872936278" Dst="-1" /><file name="jqueryFileTree.pl" server="Macintosh HD/Applications/MAMP/htdocs/Final/" local="3317431936" remote="318763443710328448" Dst="-1" /><file name="jqueryFileTree.py" server="Macintosh HD/Applications/MAMP/htdocs/Final/" local="3297590354" remote="318763443690486866" Dst="-1" /><file name="jqueryFileTree.rb" server="Macintosh HD/Applications/MAMP/htdocs/Final/" local="3298766486" remote="318763443691662998" Dst="-1" /><file name="jqueryFileTree_huck.lasso" server="Macintosh HD/Applications/MAMP/htdocs/Final/" local="3297590372" remote="318763443690486884" Dst="-1" /><file name="jqueryFileTree_sabourdin.lasso" server="Macintosh HD/Applications/MAMP/htdocs/Final/" local="3294739072" remote="318763443687635584" Dst="-1" /></dwsync>